src/__init__.py
src/__main__.py
src/cli.py
src/feed.py
src/filter_pipe.py
src/input.py
src/model_map.py
src/pre_filter.py
src/readme.py
src/remote_asset.py
src/rf_model.py
src/text_prediction.py
src/transformer_model.py
samples_filter-0.5.1.dist-info/LICENSE.txt
samples_filter-0.5.1.dist-info/METADATA
samples_filter-0.5.1.dist-info/WHEEL
samples_filter-0.5.1.dist-info/entry_points.txt
samples_filter-0.5.1.dist-info/top_level.txt
samples_filter-0.5.1.dist-info/RECORD
