Metadata-Version: 2.1
Name: samples-filter
Version: 0.5.1
Summary: Command-line filter for GitHub repositories that contain "samples", instead of real project or framework or library
Home-page: https://github.com/h1alexbel/samples-filter
Author: Aliaksei Bialiauski
Author-email: aliaksei.bialiauski@hey.com
License: UNKNOWN
Platform: UNKNOWN
Classifier: Development Status :: 3 - Alpha
Classifier: Intended Audience :: Developers
Classifier: License :: OSI Approved :: MIT License
Classifier: Programming Language :: Python :: 3.9
Classifier: Programming Language :: Python :: 3.10
Classifier: Programming Language :: Python :: 3.11
License-File: LICENSE.txt
Requires-Dist: joblib
Requires-Dist: pyarrow
Requires-Dist: requests
Requires-Dist: torch
Requires-Dist: transformers
Requires-Dist: typer
